flecsi_skeleton/__init__.py
flecsi_skeleton/__main__.py
flecsi_skeleton/_auxiliary_files/README.md
flecsi_skeleton/_auxiliary_files/support/env.yaml
flecsi_skeleton/_internal/fileutils.py
flecsi_skeleton/_internal/main.py
flecsi_skeleton/_internal/options.py
flecsi_skeleton/_internal/templates.py
flecsi_skeleton-0.1.0.dist-info/METADATA
flecsi_skeleton-0.1.0.dist-info/WHEEL
flecsi_skeleton-0.1.0.dist-info/entry_points.txt
flecsi_skeleton-0.1.0.dist-info/top_level.txt
flecsi_skeleton-0.1.0.dist-info/RECORD
